cloudvar
